CHANGELOG.txt
LINCENCE.txt
MANIFEST.in
README.md
requirements.txt
setup.py
test.py
tomlTest.py
bin/rst2html.py
bin/rst2html4.py
bin/rst2html5.py
bin/rst2latex.py
bin/rst2man.py
bin/rst2odt.py
bin/rst2odt_prepstyles.py
bin/rst2pseudoxml.py
bin/rst2s5.py
bin/rst2xetex.py
bin/rst2xml.py
bin/rstpep2html.py
lib/python3.9/site-packages/decorator.py
lib/python3.9/site-packages/easy_install.py
lib/python3.9/site-packages/pyparsing.py
lib/python3.9/site-packages/six.py
lib/python3.9/site-packages/sseclient.py
lib/python3.9/site-packages/typing_extensions.py
lib/python3.9/site-packages/zipp.py
lib/python3.9/site-packages/Flask-2.0.1.dist-info/entry_points.txt
lib/python3.9/site-packages/Flask-2.0.1.dist-info/top_level.txt
lib/python3.9/site-packages/Flask_RESTful-0.3.9.dist-info/AUTHORS.md
lib/python3.9/site-packages/Flask_RESTful-0.3.9.dist-info/top_level.txt
lib/python3.9/site-packages/Jinja2-3.0.1.dist-info/entry_points.txt
lib/python3.9/site-packages/Jinja2-3.0.1.dist-info/top_level.txt
lib/python3.9/site-packages/MarkupSafe-2.0.1.dist-info/top_level.txt
lib/python3.9/site-packages/PyNaCl-1.4.0.dist-info/top_level.txt
lib/python3.9/site-packages/Pygments-2.9.0.dist-info/entry_points.txt
lib/python3.9/site-packages/Pygments-2.9.0.dist-info/top_level.txt
lib/python3.9/site-packages/Werkzeug-2.0.1.dist-info/top_level.txt
lib/python3.9/site-packages/aiohttp/__init__.py
lib/python3.9/site-packages/aiohttp/abc.py
lib/python3.9/site-packages/aiohttp/base_protocol.py
lib/python3.9/site-packages/aiohttp/client.py
lib/python3.9/site-packages/aiohttp/client_exceptions.py
lib/python3.9/site-packages/aiohttp/client_proto.py
lib/python3.9/site-packages/aiohttp/client_reqrep.py
lib/python3.9/site-packages/aiohttp/client_ws.py
lib/python3.9/site-packages/aiohttp/connector.py
lib/python3.9/site-packages/aiohttp/cookiejar.py
lib/python3.9/site-packages/aiohttp/formdata.py
lib/python3.9/site-packages/aiohttp/frozenlist.py
lib/python3.9/site-packages/aiohttp/hdrs.py
lib/python3.9/site-packages/aiohttp/helpers.py
lib/python3.9/site-packages/aiohttp/http.py
lib/python3.9/site-packages/aiohttp/http_exceptions.py
lib/python3.9/site-packages/aiohttp/http_parser.py
lib/python3.9/site-packages/aiohttp/http_websocket.py
lib/python3.9/site-packages/aiohttp/http_writer.py
lib/python3.9/site-packages/aiohttp/locks.py
lib/python3.9/site-packages/aiohttp/log.py
lib/python3.9/site-packages/aiohttp/multipart.py
lib/python3.9/site-packages/aiohttp/payload.py
lib/python3.9/site-packages/aiohttp/payload_streamer.py
lib/python3.9/site-packages/aiohttp/pytest_plugin.py
lib/python3.9/site-packages/aiohttp/resolver.py
lib/python3.9/site-packages/aiohttp/signals.py
lib/python3.9/site-packages/aiohttp/streams.py
lib/python3.9/site-packages/aiohttp-3.7.4.post0.dist-info/LICENSE.txt
lib/python3.9/site-packages/aiohttp-3.7.4.post0.dist-info/top_level.txt
lib/python3.9/site-packages/aiohttp_sse_client-0.2.1.dist-info/top_level.txt
lib/python3.9/site-packages/aniso8601-9.0.1.dist-info/top_level.txt
lib/python3.9/site-packages/async_timeout-3.0.1.dist-info/top_level.txt
lib/python3.9/site-packages/attrs-21.2.0.dist-info/top_level.txt
lib/python3.9/site-packages/bleach-3.3.0.dist-info/top_level.txt
lib/python3.9/site-packages/bleach/_vendor/Django-1.11.29.dist-info/entry_points.txt
lib/python3.9/site-packages/bleach/_vendor/Django-1.11.29.dist-info/top_level.txt
lib/python3.9/site-packages/bleach/_vendor/html5lib-1.1.dist-info/top_level.txt
lib/python3.9/site-packages/certifi-2021.5.30.dist-info/top_level.txt
lib/python3.9/site-packages/cffi-1.14.5.dist-info/entry_points.txt
lib/python3.9/site-packages/cffi-1.14.5.dist-info/top_level.txt
lib/python3.9/site-packages/chardet-4.0.0.dist-info/entry_points.txt
lib/python3.9/site-packages/chardet-4.0.0.dist-info/top_level.txt
lib/python3.9/site-packages/click-8.0.1.dist-info/top_level.txt
lib/python3.9/site-packages/colorama-0.4.4.dist-info/LICENSE.txt
lib/python3.9/site-packages/colorama-0.4.4.dist-info/top_level.txt
lib/python3.9/site-packages/decorator-5.0.9.dist-info/LICENSE.txt
lib/python3.9/site-packages/decorator-5.0.9.dist-info/top_level.txt
lib/python3.9/site-packages/docutils-0.17.1.dist-info/COPYING.txt
lib/python3.9/site-packages/docutils-0.17.1.dist-info/top_level.txt
lib/python3.9/site-packages/idna-2.10.dist-info/top_level.txt
lib/python3.9/site-packages/importlib_metadata-4.6.0.dist-info/top_level.txt
lib/python3.9/site-packages/itsdangerous-2.0.1.dist-info/top_level.txt
lib/python3.9/site-packages/keyring-23.0.1.dist-info/entry_points.txt
lib/python3.9/site-packages/keyring-23.0.1.dist-info/top_level.txt
lib/python3.9/site-packages/mnemonic-0.19.dist-info/top_level.txt
lib/python3.9/site-packages/multidict-5.1.0.dist-info/top_level.txt
lib/python3.9/site-packages/packaging-20.9.dist-info/top_level.txt
lib/python3.9/site-packages/pip-21.1.3.dist-info/LICENSE.txt
lib/python3.9/site-packages/pip-21.1.3.dist-info/entry_points.txt
lib/python3.9/site-packages/pip-21.1.3.dist-info/top_level.txt
lib/python3.9/site-packages/pkginfo-1.7.0.dist-info/LICENSE.txt
lib/python3.9/site-packages/pkginfo-1.7.0.dist-info/entry_points.txt
lib/python3.9/site-packages/pkginfo-1.7.0.dist-info/top_level.txt
lib/python3.9/site-packages/pycparser-2.20.dist-info/top_level.txt
lib/python3.9/site-packages/pyparsing-2.4.7.dist-info/top_level.txt
lib/python3.9/site-packages/python_dateutil-2.8.1.dist-info/top_level.txt
lib/python3.9/site-packages/pytz-2021.1.dist-info/LICENSE.txt
lib/python3.9/site-packages/pytz-2021.1.dist-info/top_level.txt
lib/python3.9/site-packages/readme_renderer-29.0.dist-info/entry_points.txt
lib/python3.9/site-packages/readme_renderer-29.0.dist-info/top_level.txt
lib/python3.9/site-packages/requests-2.25.1.dist-info/top_level.txt
lib/python3.9/site-packages/requests_toolbelt-0.9.1.dist-info/top_level.txt
lib/python3.9/site-packages/rfc3986-1.5.0.dist-info/top_level.txt
lib/python3.9/site-packages/setuptools-49.2.1.dist-info/dependency_links.txt
