Metadata-Version: 2.1
Name: sep10
Version: 0.0.2
Summary: Stellar Sep10 Modules
Home-page: https://github.com/garantor/StellarSep10
Author: Afolabi
Author-email: afolabisunday31@yahoo.com
License: MIT
Keywords: python,Stellar,Blockchain,Sep10
Platform: UNKNOWN
Classifier: Development Status :: 5 - Production/Stable
Classifier: Intended Audience :: Education
Classifier: Operating System :: Microsoft :: Windows :: Windows 10
Classifier: License :: OSI Approved :: MIT License
Classifier: Programming Language :: Python :: 3
